radfil/__init__.py
radfil/plot.py
radfil/plummer.py
radfil/profile_tools.py
radfil/radfil_class.py
radfil/styles.py
radfil-1.1.5.dist-info/LICENSE
radfil-1.1.5.dist-info/METADATA
radfil-1.1.5.dist-info/WHEEL
radfil-1.1.5.dist-info/top_level.txt
radfil-1.1.5.dist-info/RECORD
