Metadata-Version: 2.1
Name: radfil
Version: 1.1.5
Summary: Build radial density profiles for interstellar filaments
Home-page: http://github.com/catherinezucker/radfil
Download-URL: https://api.github.com/repos/catherinezucker/radfil/zipball/master
Author: ['Catherine Zucker', 'Hope Chen']
Author-email: catherine.zucker@cfa.harvard.edu
Keywords: astrophysics,radfil,filaments
License-File: LICENSE
Requires-Dist: numpy
Requires-Dist: scipy
Requires-Dist: matplotlib
Requires-Dist: astropy
Requires-Dist: shapely
Requires-Dist: scikit-learn
Requires-Dist: scikit-image
Requires-Dist: networkx
Requires-Dist: pandas
